./.gitignore
./PKG-INFO
./README.md
./pyproject.toml
./scwrypts/__init__.py
./scwrypts/env.py
./scwrypts/data/__init__.py
./scwrypts/data/converter.py
./scwrypts/data/test_converter.py
./scwrypts/fzf/__init__.py
./scwrypts/fzf/client.py
./scwrypts/http/__init__.py
./scwrypts/http/client.py
./scwrypts/http/conftest.py
./scwrypts/http/test_client.py
./scwrypts/http/directus/__init__.py
./scwrypts/http/directus/client.py
./scwrypts/http/directus/collections.py
./scwrypts/http/directus/conftest.py
./scwrypts/http/directus/fields.py
./scwrypts/http/directus/graphql.py
./scwrypts/http/directus/test_client.py
./scwrypts/http/directus/test_graphql.py
./scwrypts/http/discord/__init__.py
./scwrypts/http/discord/client.py
./scwrypts/http/discord/conftest.py
./scwrypts/http/discord/send_message.py
./scwrypts/http/discord/test_client.py
./scwrypts/http/discord/test_send_message.py
./scwrypts/http/linear/__init__.py
./scwrypts/http/linear/client.py
./scwrypts/http/linear/conftest.py
./scwrypts/http/linear/graphql.py
./scwrypts/http/linear/test_client.py
./scwrypts/http/linear/test_graphql.py
./scwrypts/io/__init__.py
./scwrypts/io/combined_io_stream.py
./scwrypts/redis/__init__.py
./scwrypts/redis/client.py
./scwrypts/scwrypts/__init__.py
./scwrypts/scwrypts/exceptions.py
./scwrypts/scwrypts/execute.py
./scwrypts/scwrypts/interactive.py
./scwrypts/scwrypts/scwrypts.py
./scwrypts/scwrypts/test_scwrypts.py
./scwrypts/test/__init__.py
./scwrypts/test/character_set.py
./scwrypts/test/exceptions.py
./scwrypts/test/generate.py
./scwrypts/test/test_generate.py
./scwrypts/twilio/__init__.py
./scwrypts/twilio/client.py
./scwrypts/twilio/send_sms.py
scwrypts-5.0.0.dist-info/METADATA
scwrypts-5.0.0.dist-info/WHEEL
scwrypts-5.0.0.dist-info/RECORD
