Metadata-Version: 2.4
Name: scwrypts
Version: 5.0.0
Summary: scwrypts library and invoker
Project-URL: homepage, https://github.com/wrynegade/scwrypts
Project-URL: issues, https://github.com/wrynegade/scwrypts/issues
Author-email: yage <yage@yage.io>
License-Expression: GPL-3.0-or-later
Classifier: License :: OSI Approved :: GNU General Public License v3 or later (GPLv3+)
Classifier: Programming Language :: Python :: 3
Classifier: Programming Language :: Python :: 3.10
Classifier: Programming Language :: Python :: 3.11
Classifier: Programming Language :: Python :: 3.12
Requires-Python: >=3.10
Requires-Dist: bpython
Requires-Dist: pyfzf
Requires-Dist: pyyaml
Requires-Dist: redis
Requires-Dist: twilio
Provides-Extra: dev
Requires-Dist: pylint; extra == 'dev'
Provides-Extra: test
Requires-Dist: pytest; extra == 'test'
